cpslo_orbits/__init__.py
cpslo_orbits/astroconsts.py
cpslo_orbits/observations.py
cpslo_orbits/orbitalcore.py
cpslo_orbits/perturbations.py
cpslo_orbits/relativemotion.py
cpslo_orbits-0.1.1.dist-info/LICENSE
cpslo_orbits-0.1.1.dist-info/METADATA
cpslo_orbits-0.1.1.dist-info/WHEEL
cpslo_orbits-0.1.1.dist-info/top_level.txt
cpslo_orbits-0.1.1.dist-info/RECORD
