Metadata-Version: 2.1
Name: cpslo-orbits
Version: 0.1.1
Summary: Small and simple package for basic Orbital Mechanics principles. Structured after Cal Poly SLO AERO Orbits I-III
Author-email: Gagandeep Thapar <gsthapar+om_pkg@gmail.com>, Kira Abercromby <kabercro@calpoly.edu>
Project-URL: Homepage, https://github.com/gagandeepthapar/OrbitalMechanics
Project-URL: Bug Tracker, https://github.com/gagandeepthapar/OrbitalMechanics/issues
Classifier: Programming Language :: Python :: 3
Classifier: License :: OSI Approved :: MIT License
Classifier: Operating System :: OS Independent
Requires-Python: >=3.10
License-File: LICENSE
Requires-Dist: pymap3d
Requires-Dist: matplotlib
Requires-Dist: numpy
Requires-Dist: pandas
Requires-Dist: pylint
Requires-Dist: pytest
Requires-Dist: pytest-cov
Requires-Dist: pytest-pylint
Requires-Dist: pytest-sugar
Requires-Dist: scipy
